flask_pocket.py
flask_pocket-1.0.2.dist-info/LICENSE
flask_pocket-1.0.2.dist-info/METADATA
flask_pocket-1.0.2.dist-info/WHEEL
flask_pocket-1.0.2.dist-info/top_level.txt
flask_pocket-1.0.2.dist-info/RECORD
