Metadata-Version: 2.2
Name: flask-pocket
Version: 1.0.2
Summary: Flask extension to integrate PocketBase
Home-page: https://github.com/codewithmpia/flask_pocket
Author: codewithmpia
Author-email: codewithmpia@gmail.com
Project-URL: Source, https://github.com/codewithmpia/flask_pocket
Project-URL: Tracker, https://github.com/codewithmpia/flask_pocket/issues
Project-URL: Author, https://github.com/codewithmpia
Classifier: Development Status :: 5 - Production/Stable
Classifier: Intended Audience :: Developers
Classifier: License :: OSI Approved :: MIT License
Classifier: Programming Language :: Python :: 3
Classifier: Framework :: Flask
License-File: LICENSE
Requires-Dist: Flask
Requires-Dist: pocketbase
Dynamic: author
Dynamic: author-email
Dynamic: classifier
Dynamic: description
Dynamic: description-content-type
Dynamic: home-page
Dynamic: project-url
Dynamic: requires-dist
Dynamic: summary
